Workbook

Sheet Read me
A1: File B · Search terms report (1–27 Sep 2026)
A2: Synthetic training data created for this workshop. It is NOT Forbes Advisor data. Brand, lender, insurer, software and competitor names are fictional; competitor domains use the reserved .example suffix.
A4: What is in this file
A5: The September search terms report for all four campaigns. Match type "AI Max" marks terms matched by AI Max for Search (from September 2026, Google is upgrading Search campaigns that use campaign-level broad match or automatically created assets to AI Max). Low-volume terms Google does not show are excluded, so totals are about 85% of campaign spend.
A6: Your task (Module 3, Lab 3a: Search-term mining)
A7: Filter to your team's campaign. Three steps, one hand-in. 1) Label each term by intent with Copilot (Allow editing, prompt P08): Core (on-product, including research about choosing, pricing or eligibility), Winner to add, Informational, Off-product, Navigational (existing customers), Policy or brand risk, Competitor. 2) Total the wasted spend and make Copilot show the formula (P09); Team Loans also notes the revenue those wasted terms earned (needed in the Budget War Room). 3) Name your top negative theme and check it does not block buyers (P03, then P27 against the existing lists). Hand in two things: wasted spend ($ and % of cost) and your top negative theme.
A8: If you finish early (not scored): list "Winner to add" terms (an AI Max- or broad-matched term that is not yet a keyword, with 5+ click-outs and ROAS at or above your target) and compare AI Max terms with keyword-matched terms (P10).
A9: What counts as wasted spend
A10: Count as waste: Informational (definitions and how-it-works questions), Off-product (other products or jobs), Navigational (existing customers of a partner: login, payments, support) and Policy or brand risk. Research about choosing, pricing or eligibility is buyer intent: keep it. Competitor terms are a separate decision: judge them on ROAS, and do not count them as waste.
A11: Record negatives in the "My negatives" sheet. The yellow row is an example and a real negative: keep it or replace it. Column E counts a term as blocked when it contains the negative as whole words, like a phrase-match negative; read the matched terms before you trust the total. "Existing negative lists" shows the account's shared lists: check a new negative against them first (prompt P27).
A12: Watch out: a term with zero click-outs is not the only kind of waste, a term that converts can still need excluding for policy or brand reasons, and a negative theme such as "how to" can block buyers.
A13: Metric definitions
... A22: 4. Check before you trust: ask Copilot to show the formula it used, recompute one number yourself, and confirm totals match the source table.

Sheet Search terms
A1: Search term | B1: Campaign | C1: Ad group | D1: Match type | E1: Impressions | F1: Clicks | G1: Cost (USD) | H1: Click-outs | I1: Revenue (USD)
A2: crm software | B2: US | Business Software | CRM | C2: CRM - Generic | D2: Phrase match | E2: 9744 | F2: 467 | G2: 5569.93 | H2: 90 | I2: 6477.83
A3: best crm tools | B3: US | Business Software | CRM | C3: CRM Comparison | D3: Exact match | E3: 4836 | F3: 252 | G3: 3824.56 | H3: 40 | I3: 2715.55
A4: crm comparison | B4: US | Business Software | CRM | C4: CRM Comparison | D4: Exact match | E4: 3504 | F4: 190 | G4: 2417.3 | H4: 47 | I4: 3199.95
A5: best crm platforms | B5: US | Business Software | CRM | C5: CRM Comparison | D5: Phrase match | E5: 2636 | F5: 129 | G5: 1979.76 | H5: 26 | I5: 1600.76
A6: compare crm software | B6: US | Business Software | CRM | C6: CRM Comparison | D6: Exact match | E6: 2290 | F6: 147 | G6: 1950.18 | H6: 35 | I6: 2082.98
A7: crm solutions | B7: US | Business Software | CRM | C7: CRM - Generic | D7: Exact match | E7: 1874 | F7: 121 | G7: 1626.24 | H7: 24 | I7: 1682.12
A8: crm software comparison | B8: US | Business Software | CRM | C8: CRM Comparison | D8: Phrase match | E8: 2480 | F8: 122 | G8: 1472.12 | H8: 21 | I8: 1455.64
A9: top crm systems | B9: US | Business Software | CRM | C9: CRM Comparison | D9: Phrase match | E9: 2941 | F9: 119 | G9: 1434.53 | H9: 29 | I9: 1850.44
A10: crm vendors | B10: US | Business Software | CRM | C10: CRM - Generic | D10: Phrase match | E10: 2208 | F10: 106 | G10: 1373.97 | H10: 24 | I10: 1727.34
A11: crm software pricing comparison | B11: US | Business Software | CRM | C11: CRM Pricing | D11: Exact match | E11: 1612 | F11: 90 | G11: 1320.09 | H11: 7 | I11: 461.7
A12: sales crm | B12: US | Business Software | CRM | C12: CRM - Generic | D12: Phrase match | E12: 2232 | F12: 98 | G12: 1318.39 | H12: 12 | I12: 757.52
A13: best crm 2026 | B13: US | Business Software | CRM | C13: CRM Comparison | D13: Exact match | E13: 1799 | F13: 94 | G13: 1305.67 | H13: 23 | I13: 1451.95
... A404: pet store near me | B404: US | Pet Insurance | Comparison | C404: Pet Insurance - Generic | D404: Broad match | E404: 652 | F404: 13 | G404: 26.8 | H404: 0 | I404: 0

Sheet My negatives
A1: My negatives (fill in)
A2: Legend: pick your campaign in B3 first. Then type one negative per row in the white rows below the yellow example (a real negative: keep it or replace it). Column E fills itself: the September cost of every search term in your campaign that contains the negative as whole words, like a phrase-match negative. Score slips use this figure.
A3: Your campaign: | B3: US | Personal Loans | Comparison
A4: Negative keyword | B4: Negative match type | C4: Level (campaign / ad group / shared list) | D4: Reason (intent category) | E4: Spend it would have blocked in Sep (USD) | F4: Checked by Challenger?
A5: calculator | B5: Phrase | C5: Shared list: Informational modifiers | D5: Informational | E5: =IF(A5="","",SUMPRODUCT(ISNUMBER(SEARCH(" "&TRIM(A5)&" "," "&'Search terms'!$A$2:$A$404&" "))*('Search terms'!$B$2:$B$404=$B$3)*'Search terms'!$G$2:$G$404)) -> 2433.2 | F5: Yes
E6: =IF(A6="","",SUMPRODUCT(ISNUMBER(SEARCH(" "&TRIM(A6)&" "," "&'Search terms'!$A$2:$A$404&" "))*('Search terms'!$B$2:$B$404=$B$3)*'Search terms'!$G$2:$G$404))
E7: =IF(A7="","",SUMPRODUCT(ISNUMBER(SEARCH(" "&TRIM(A7)&" "," "&'Search terms'!$A$2:$A$404&" "))*('Search terms'!$B$2:$B$404=$B$3)*'Search terms'!$G$2:$G$404))
E8: =IF(A8="","",SUMPRODUCT(ISNUMBER(SEARCH(" "&TRIM(A8)&" "," "&'Search terms'!$A$2:$A$404&" "))*('Search terms'!$B$2:$B$404=$B$3)*'Search terms'!$G$2:$G$404))
E9: =IF(A9="","",SUMPRODUCT(ISNUMBER(SEARCH(" "&TRIM(A9)&" "," "&'Search terms'!$A$2:$A$404&" "))*('Search terms'!$B$2:$B$404=$B$3)*'Search terms'!$G$2:$G$404))
E10: =IF(A10="","",SUMPRODUCT(ISNUMBER(SEARCH(" "&TRIM(A10)&" "," "&'Search terms'!$A$2:$A$404&" "))*('Search terms'!$B$2:$B$404=$B$3)*'Search terms'!$G$2:$G$404))
E11: =IF(A11="","",SUMPRODUCT(ISNUMBER(SEARCH(" "&TRIM(A11)&" "," "&'Search terms'!$A$2:$A$404&" "))*('Search terms'!$B$2:$B$404=$B$3)*'Search terms'!$G$2:$G$404))
E12: =IF(A12="","",SUMPRODUCT(ISNUMBER(SEARCH(" "&TRIM(A12)&" "," "&'Search terms'!$A$2:$A$404&" "))*('Search terms'!$B$2:$B$404=$B$3)*'Search terms'!$G$2:$G$404))
E13: =IF(A13="","",SUMPRODUCT(ISNUMBER(SEARCH(" "&TRIM(A13)&" "," "&'Search terms'!$A$2:$A$404&" "))*('Search terms'!$B$2:$B$404=$B$3)*'Search terms'!$G$2:$G$404))
E14: =IF(A14="","",SUMPRODUCT(ISNUMBER(SEARCH(" "&TRIM(A14)&" "," "&'Search terms'!$A$2:$A$404&" "))*('Search terms'!$B$2:$B$404=$B$3)*'Search terms'!$G$2:$G$404))
E15: =IF(A15="","",SUMPRODUCT(ISNUMBER(SEARCH(" "&TRIM(A15)&" "," "&'Search terms'!$A$2:$A$404&" "))*('Search terms'!$B$2:$B$404=$B$3)*'Search terms'!$G$2:$G$404))
E16: =IF(A16="","",SUMPRODUCT(ISNUMBER(SEARCH(" "&TRIM(A16)&" "," "&'Search terms'!$A$2:$A$404&" "))*('Search terms'!$B$2:$B$404=$B$3)*'Search terms'!$G$2:$G$404))
E17: =IF(A17="","",SUMPRODUCT(ISNUMBER(SEARCH(" "&TRIM(A17)&" "," "&'Search terms'!$A$2:$A$404&" "))*('Search terms'!$B$2:$B$404=$B$3)*'Search terms'!$G$2:$G$404))
... E25: =IF(A25="","",SUMPRODUCT(ISNUMBER(SEARCH(" "&TRIM(A25)&" "," "&'Search terms'!$A$2:$A$404&" "))*('Search terms'!$B$2:$B$404=$B$3)*'Search terms'!$G$2:$G$404))

Sheet Existing negative lists
A1: Existing shared negative keyword lists in the account (phrase match). Not yet applied to the comparison campaigns in this file.
A3: List | B3: Negative
A4: Informational modifiers | B4: definition
A5: Informational modifiers | B5: meaning
A6: Informational modifiers | B6: wiki
A7: Informational modifiers | B7: history of
A8: Jobs and careers | B8: jobs
A9: Jobs and careers | B9: careers
A10: Jobs and careers | B10: salary
A11: Jobs and careers | B11: internship
A12: Existing customers | B12: login
A13: Existing customers | B13: sign in
A14: Existing customers | B14: customer service
A15: Existing customers | B15: phone number
